pylogrus/__init__.py
pylogrus/base.py
pylogrus/json_formatter.py
pylogrus/text_formatter.py
pylogrus-0.4.0.dist-info/METADATA
pylogrus-0.4.0.dist-info/RECORD
pylogrus-0.4.0.dist-info/WHEEL
pylogrus-0.4.0.dist-info/top_level.txt
tests/__init__.py
tests/test_json_formatter.py
tests/test_text_formatter.py
