Metadata-Version: 2.1
Name: pylogrus
Version: 0.4.0
Summary: PyLogrus is a structured logger for Python
Home-page: https://github.com/vmig/pylogrus
Author: Vitalii Myhal
Author-email: 6934861+vmig@users.noreply.github.com
License: MIT License
Keywords: logger logging colorize output json extra fields
Platform: UNKNOWN
Classifier: Development Status :: 3 - Alpha
Classifier: Environment :: Console
Classifier: Intended Audience :: Customer Service
Classifier: Intended Audience :: Developers
Classifier: Intended Audience :: System Administrators
Classifier: License :: OSI Approved :: MIT License
Classifier: Operating System :: POSIX :: Linux
Classifier: Topic :: System :: Logging
Classifier: Programming Language :: Python
Classifier: Programming Language :: Python :: 2.7
Classifier: Programming Language :: Python :: 3
Classifier: Programming Language :: Python :: 3.5
Classifier: Programming Language :: Python :: 3.6
Provides-Extra: dev
Provides-Extra: test
